ontolocy/__init__.py
ontolocy/cli.py
ontolocy/dataorigin.py
ontolocy/mixin.py
ontolocy/node.py
ontolocy/relationship.py
ontolocy/utils.py
ontolocy/models/__init__.py
ontolocy/models/actortype.py
ontolocy/models/asn.py
ontolocy/models/banner.py
ontolocy/models/campaign.py
ontolocy/models/capecpattern.py
ontolocy/models/cobaltstrikebeacon.py
ontolocy/models/cobaltstrikewatermark.py
ontolocy/models/control.py
ontolocy/models/controlvalidationtest.py
ontolocy/models/country.py
ontolocy/models/cpe.py
ontolocy/models/cve.py
ontolocy/models/cwe.py
ontolocy/models/cyberharm.py
ontolocy/models/detection.py
ontolocy/models/dnsrecord.py
ontolocy/models/domainname.py
ontolocy/models/exploit.py
ontolocy/models/host.py
ontolocy/models/implementationguidance.py
ontolocy/models/incident.py
ontolocy/models/intrusionset.py
ontolocy/models/ip.py
ontolocy/models/jarmhash.py
ontolocy/models/listeningsocket.py
ontolocy/models/macaddress.py
ontolocy/models/mitreattackcampaign.py
ontolocy/models/mitreattackdatacomponent.py
ontolocy/models/mitreattackdatasource.py
ontolocy/models/mitreattackgroup.py
ontolocy/models/mitreattackmatrix.py
ontolocy/models/mitreattackmitigation.py
ontolocy/models/mitreattacksoftware.py
ontolocy/models/mitreattacktactic.py
ontolocy/models/mitreattacktechnique.py
ontolocy/models/networkservice.py
ontolocy/models/organisation.py
ontolocy/models/port.py
ontolocy/models/report.py
ontolocy/models/sector.py
ontolocy/models/threatactor.py
ontolocy/models/url.py
ontolocy/models/useraccount.py
ontolocy/models/x509certificate.py
ontolocy/tools/__init__.py
ontolocy/tools/capec.py
ontolocy/tools/cisa_kev.py
ontolocy/tools/ctid_attack_mappings.py
ontolocy/tools/cwe.py
ontolocy/tools/ht_dns.py
ontolocy/tools/ht_ptrip.py
ontolocy/tools/ht_revdns.py
ontolocy/tools/ht_subdomain.py
ontolocy/tools/mitre_attack.py
ontolocy/tools/nist_csf_1.py
ontolocy/tools/nist_csf_2.py
ontolocy/tools/nist_sp80053_v4.py
ontolocy/tools/nist_sp80053_v5.py
ontolocy/tools/nvd.py
ontolocy-0.9.3.dist-info/licenses/LICENSE
ontolocy-0.9.3.dist-info/METADATA
ontolocy-0.9.3.dist-info/WHEEL
ontolocy-0.9.3.dist-info/entry_points.txt
ontolocy-0.9.3.dist-info/top_level.txt
ontolocy-0.9.3.dist-info/RECORD
