Metadata-Version: 2.4
Name: ontolocy
Version: 0.9.3
Summary: A Python package for modeling cybersecurity data in a Neo4j graph database.
Home-page: https://github.com/ontolocy/ontolocy-lib
Author: Ontolocy
Classifier: Programming Language :: Python :: 3
Classifier: License :: OSI Approved :: MIT License
Classifier: Operating System :: OS Independent
Requires-Python: >=3.9
License-File: LICENSE
Requires-Dist: pydantic<3,>=2
Requires-Dist: neontology<3,>=2
Requires-Dist: pandas<3,>=2
Requires-Dist: click<9,>=8
Requires-Dist: xmltodict
Requires-Dist: requests
Requires-Dist: openpyxl
Requires-Dist: PyYAML
Provides-Extra: shodan
Requires-Dist: shodan; extra == "shodan"
Provides-Extra: all
Requires-Dist: shodan; extra == "all"
Dynamic: license-file
